MANIFEST.in
README.md
setup.py
Corpus/Corpus.py
Corpus/CorpusDict.csv
Corpus/__init__.py
Corpus.egg-info/PKG-INFO
Corpus.egg-info/SOURCES.txt
Corpus.egg-info/dependency_links.txt
Corpus.egg-info/not-zip-safe
Corpus.egg-info/top_level.txt